{
  "name": "Neofloss",
  "version": "1.0.0",
  "mode": "dark",
  "inherentMode": "dark",
  "colors": {
    "background": "#1C1B1D",
    "foreground": "#D8B2DE",
    "foregroundStrong": "#FAD6FF",
    "muted": "#282529",
    "mutedForeground": "#695A6B",
    "tooltip": "#322D33",
    "tooltipForeground": "#FAD6FF",
    "primary": "#BEA7FF",
    "primaryForeground": "#1C1B1D",
    "secondary": "#282529",
    "secondaryForeground": "#D8B2DE",
    "accent": "#44D1B9",
    "accentForeground": "#1C1B1D",
    "accentMuted": "#4B3F4D",
    "link": "#7497E6",
    "linkHover": "#AAC4FF",
    "destructive": "#DA1173",
    "destructiveForeground": "#FAD6FF",
    "border": "#282529",
    "ring": "#8B70DA",
    "tag": "#8B70DA",
    "tagForeground": "#FAD6FF",
    "popover": "#282529",
    "popoverForeground": "#D8B2DE",
    "card": "#282529",
    "cardForeground": "#D8B2DE",
    "input": "#4B3F4D",
    "accentSecondary": "#60C2E0",
    "accentSecondaryForeground": "#1C1B1D",
    "accentTertiary": "#EA5594",
    "accentTertiaryForeground": "#1C1B1D",
    "tagSecondary": "#322D33",
    "tagSecondaryForeground": "#BEA7FF"
  }
}
